django_brotli/__init__.py
django_brotli/middleware.py
django_brotli/py.typed
django_brotli-0.4.0.dist-info/LICENSE
django_brotli-0.4.0.dist-info/METADATA
django_brotli-0.4.0.dist-info/WHEEL
django_brotli-0.4.0.dist-info/RECORD
