Metadata-Version: 2.3
Name: django-brotli
Version: 0.4.0
Summary: Middleware that compresses response using brotli algorithm.
Home-page: https://github.com/illagrenan/django-brotli
License: MIT
Author: Václav Dohnal
Author-email: vaclav.dohnal@gmail.com
Requires-Python: >=3.10, <3.15
Classifier: Development Status :: 4 - Beta
Classifier: Environment :: Web Environment
Classifier: Framework :: Django
Classifier: Framework :: Django :: 4
Classifier: Framework :: Django :: 5.0
Classifier: Framework :: Django :: 5.1
Classifier: Framework :: Django :: 5.2
Classifier: Framework :: Django :: 6.0
Classifier: Intended Audience :: Developers
Classifier: License :: OSI Approved :: MIT License
Classifier: Natural Language :: English
Classifier: Operating System :: OS Independent
Classifier: Programming Language :: Python :: 3
Classifier: Programming Language :: Python :: 3.10
Classifier: Programming Language :: Python :: 3.11
Classifier: Programming Language :: Python :: 3.12
Classifier: Programming Language :: Python :: 3.13
Classifier: Programming Language :: Python :: 3 :: Only
Classifier: Programming Language :: Python :: 3.14
Requires-Dist: brotli (>=1.1,<2.0)
Requires-Dist: django (>=4,<7)
Project-URL: Bug Tracker, https://github.com/illagrenan/django-brotli/issues
Project-URL: Documentation, https://github.com/illagrenan/django-brotli
Project-URL: Repository, https://github.com/illagrenan/django-brotli
